.travis.yml
AUTHORS
CONTRIBUTING.rst
ChangeLog
LICENSE
Makefile
README.rst
announce.rst
requirements.txt
setup.cfg
setup.py
tester.py
tox.ini
tweets.png
whatthewhat/__init__.py
whatthewhat/execfile.py
whatthewhat/main.py
whatthewhat.egg-info/PKG-INFO
whatthewhat.egg-info/SOURCES.txt
whatthewhat.egg-info/dependency_links.txt
whatthewhat.egg-info/entry_points.txt
whatthewhat.egg-info/not-zip-safe
whatthewhat.egg-info/requires.txt
whatthewhat.egg-info/top_level.txt