Metadata-Version: 1.1
Name: whatthewhat
Version: 1.0
Summary: Launch a Google search for exceptions from Python apps
Home-page: https://github.com/dhellmann/whatthewhat
Author: Doug Hellmann
Author-email: doug@doughellmann.com
License: UNKNOWN
Platform: UNKNOWN
Classifier: Development Status :: 5 - Production/Stable
Classifier: License :: OSI Approved :: Apache Software License
Classifier: Programming Language :: Python
Classifier: Programming Language :: Python :: 2
Classifier: Programming Language :: Python :: 2.7
Classifier: Intended Audience :: Developers
Classifier: Environment :: Console
